PDFAgent/__init__.py
PDFAgent/agent.py
PDFAgent-0.2.3.dist-info/LICENSE
PDFAgent-0.2.3.dist-info/METADATA
PDFAgent-0.2.3.dist-info/WHEEL
PDFAgent-0.2.3.dist-info/top_level.txt
PDFAgent-0.2.3.dist-info/RECORD
