Metadata-Version: 2.1
Name: PDFAgent
Version: 0.2.3
Summary: Production Ready PDF Agent
Home-page: https://github.com/mr-gpt/PDFAgent
Author: Twilix Team
Author-email: jacky@twilix.io
License-File: LICENSE
Requires-Dist: blitzchain (>=0.8.2)
